flex_optimization/__init__.py
flex_optimization/core/__init__.py
flex_optimization/core/data_point.py
flex_optimization/core/logger_.py
flex_optimization/core/method.py
flex_optimization/core/method_subclass.py
flex_optimization/core/problem.py
flex_optimization/core/recorder.py
flex_optimization/core/stop_criteria.py
flex_optimization/core/utils.py
flex_optimization/core/variable.py
flex_optimization/core/visualize.py
flex_optimization/extras/__init__.py
flex_optimization/extras/batch.py
flex_optimization/methods/__init__.py
flex_optimization/methods/_create_readme.py
flex_optimization/methods/active_methods/__init__.py
flex_optimization/methods/active_methods/_sampler.py
flex_optimization/methods/active_methods/baysian_dragon.py
flex_optimization/methods/active_methods/sampler/__init__.py
flex_optimization/methods/active_methods/sampler/halton.py
flex_optimization/methods/active_methods/sampler/latin_hypercube.py
flex_optimization/methods/active_methods/sampler/multivariate_normal.py
flex_optimization/methods/active_methods/sampler/random_pick.py
flex_optimization/methods/active_methods/sampler/sobol.py
flex_optimization/methods/active_methods/sampler/utils.py
flex_optimization/methods/active_methods/scipy/BFGS.py
flex_optimization/methods/active_methods/scipy/__init__.py
flex_optimization/methods/active_methods/scipy/_scipy_base.py
flex_optimization/methods/active_methods/scipy/basinhopping.py
flex_optimization/methods/active_methods/scipy/broyden1.py
flex_optimization/methods/active_methods/scipy/dual_anneal.py
flex_optimization/methods/active_methods/scipy/nelder_mead.py
flex_optimization/methods/active_methods/scipy/powell.py
flex_optimization/methods/active_methods/scipy/trust_constraint.py
flex_optimization/methods/passive_methods/__init__.py
flex_optimization/methods/passive_methods/covariance.py
flex_optimization/methods/passive_methods/factorial.py
flex_optimization/methods/passive_methods/multi_covariance.py
flex_optimization-0.0.7.dist-info/LICENSE.txt
flex_optimization-0.0.7.dist-info/METADATA
flex_optimization-0.0.7.dist-info/WHEEL
flex_optimization-0.0.7.dist-info/top_level.txt
flex_optimization-0.0.7.dist-info/RECORD
