Metadata-Version: 2.1
Name: flex-optimization
Version: 0.0.7
Summary: simple but flexable optimization package
Home-page: https://github.com/dylanwal/flex_optimization
Author: Dylan Walsh
License: BSD
Platform: any
Classifier: License :: OSI Approved :: BSD License
Classifier: Programming Language :: Python :: 3
Classifier: Programming Language :: Python :: 3 :: Only
Classifier: Programming Language :: Python :: 3.10
Requires-Python: >=3.10
License-File: LICENSE.txt
Requires-Dist: numpy (>=1.21.5)
Requires-Dist: plotly (>=5.6.0)
Requires-Dist: scipy (>=1.7.3)
Requires-Dist: pandas (>=1.4.2)
